helloworld.py
helloworld29553-0.0.1.dist-info/METADATA
helloworld29553-0.0.1.dist-info/WHEEL
helloworld29553-0.0.1.dist-info/top_level.txt
helloworld29553-0.0.1.dist-info/RECORD
