Metadata-Version: 2.1
Name: helloworld29553
Version: 0.0.1
Summary: Say hello
Home-page: https://github.com/elunna/helloworld
Author: Erik Lunna
Author-email: eslunna@gmail.com
License: UNKNOWN
Platform: UNKNOWN
